relab/__init__.py
relab/agents/AgentInterface.py
relab/agents/BetaHMM.py
relab/agents/BetaVAE.py
relab/agents/CDQN.py
relab/agents/DDQN.py
relab/agents/DQN.py
relab/agents/DiscreteHMM.py
relab/agents/DiscreteVAE.py
relab/agents/DuelingDDQN.py
relab/agents/DuelingDQN.py
relab/agents/HMM.py
relab/agents/IQN.py
relab/agents/JointHMM.py
relab/agents/JointVAE.py
relab/agents/MDQN.py
relab/agents/NoisyCDQN.py
relab/agents/NoisyDDQN.py
relab/agents/NoisyDQN.py
relab/agents/PrioritizedDDQN.py
relab/agents/PrioritizedDQN.py
relab/agents/PrioritizedMDQN.py
relab/agents/QRDQN.py
relab/agents/RainbowDQN.py
relab/agents/RainbowIQN.py
relab/agents/Random.py
relab/agents/VAE.py
relab/agents/VariationalModel.py
relab/agents/__init__.py
relab/agents/factory.py
relab/agents/memory/ReplayBuffer.py
relab/agents/memory/__init__.py
relab/agents/networks/CategoricalDeepQNetworks.py
relab/agents/networks/DecoderNetworks.py
relab/agents/networks/DeepQNetworks.py
relab/agents/networks/DuelingDeepQNetworks.py
relab/agents/networks/EncoderNetworks.py
relab/agents/networks/QuantileDeepQNetworks.py
relab/agents/networks/RainbowDeepQNetwork.py
relab/agents/networks/TransitionNetworks.py
relab/agents/networks/__init__.py
relab/agents/networks/layers/Categorical.py
relab/agents/networks/layers/ConvTranspose2d.py
relab/agents/networks/layers/DiagonalGaussian.py
relab/agents/networks/layers/__init__.py
relab/agents/schedule/ExponentialSchedule.py
relab/agents/schedule/PiecewiseLinearSchedule.py
relab/agents/schedule/__init__.py
relab/cpp/inc/agents/memory/compressors.hpp
relab/cpp/inc/agents/memory/data_buffer.hpp
relab/cpp/inc/agents/memory/experience.hpp
relab/cpp/inc/agents/memory/frame_buffer.hpp
relab/cpp/inc/agents/memory/frame_storage.hpp
relab/cpp/inc/agents/memory/priority_tree.hpp
relab/cpp/inc/agents/memory/replay_buffer.hpp
relab/cpp/inc/helpers/debug.hpp
relab/cpp/inc/helpers/deque.hpp
relab/cpp/inc/helpers/serialize.hpp
relab/cpp/inc/helpers/thread_pool.hpp
relab-0.5.3.dist-info/LICENSE.md
relab-0.5.3.dist-info/METADATA
relab-0.5.3.dist-info/WHEEL
relab-0.5.3.dist-info/entry_points.txt
relab-0.5.3.dist-info/RECORD
