Metadata-Version: 2.3
Name: relab
Version: 0.5.3
Summary: Reinforcement learning made easy with prebuilt agents, Gym integration, and performance visualization.
License: # MIT License
Keywords: pytorch,reinforcement learning,deep learning
Author: Théophile Champion
Author-email: theoph.champion@gmail.com
Requires-Python: >=3.12,<4.0
Classifier: Programming Language :: Python :: 3
Classifier: License :: OSI Approved :: MIT License
Classifier: Operating System :: OS Independent
Classifier: Topic :: Scientific/Engineering :: Artificial Intelligence
Requires-Dist: gymnasium[atari,other] (==1.1.1)
Requires-Dist: imageio (==2.36.0)
Requires-Dist: invoke (==2.2.0)
Requires-Dist: matplotlib (==3.9.2)
Requires-Dist: numpy (==2.2.1)
Requires-Dist: pandas (==2.2.3)
Requires-Dist: pillow (==10.4.0)
Requires-Dist: psutil (==6.1.1)
Requires-Dist: seaborn (==0.13.2)
Requires-Dist: tensorboard (==2.18.0)
Requires-Dist: torchrl (==0.6.0)
Requires-Dist: torchvision (==0.20.1)
Project-URL: Documentation, https://theophilechampion.github.io/ReLab/
Project-URL: Repository, https://github.com/TheophileChampion/ReLab/
